README
setup.py
uwsgi_manager/__init__.py
uwsgi_manager/manager.py
uwsgi_manager.egg-info/PKG-INFO
uwsgi_manager.egg-info/SOURCES.txt
uwsgi_manager.egg-info/dependency_links.txt
uwsgi_manager.egg-info/entry_points.txt
uwsgi_manager.egg-info/top_level.txt