Metadata-Version: 1.0
Name: uwsgi-manager
Version: 0.1.1
Summary: Python tool for controling the uWSGI instances.
Home-page: https://github.com/creckx/uWSGI-Manager
Author: Adam Strauch
Author-email: cx@initd.cz
License: BSD
Keywords: uwsgi
Platform: UNKNOWN
Classifier: Development Status :: 3 - Alpha
Classifier: Topic :: Utilities
Classifier: License :: OSI Approved :: BSD License
